AUTHORS.rst
CHANGELOG.rst
LICENSE
MANIFEST.in
README.rst
setup.py
django_publisher.egg-info/PKG-INFO
django_publisher.egg-info/SOURCES.txt
django_publisher.egg-info/dependency_links.txt
django_publisher.egg-info/requires.txt
django_publisher.egg-info/top_level.txt
publisher/__init__.py
publisher/admin.py
publisher/models.py
publisher/tests.py